tickersaver/__init__.py
tickersaver/cache/sqllite_cache.py
tickersaver/fetcher/kite/orders.py
tickersaver/fetcher/kite/ws_tick_fetcher.py
tickersaver/utils/log.py
zerodha_tickersaver-1.1.2.dist-info/LICENCE
zerodha_tickersaver-1.1.2.dist-info/METADATA
zerodha_tickersaver-1.1.2.dist-info/WHEEL
zerodha_tickersaver-1.1.2.dist-info/entry_points.txt
zerodha_tickersaver-1.1.2.dist-info/top_level.txt
zerodha_tickersaver-1.1.2.dist-info/RECORD
