Metadata-Version: 2.1
Name: zerodha-tickersaver
Version: 1.1.2
Summary: Get the latest price of instruments via web-sockets from zerodha
Author-email: Simon <simonmh2u@gmail.com>
Project-URL: Homepage, https://github.com/simonmh2u/TickerSaver
Keywords: zerodha,websockets,ltp,tick,nfo,options
Classifier: License :: OSI Approved :: MIT License
Classifier: Programming Language :: Python :: 3.9
Requires-Python: >=3.9
License-File: LICENCE
Requires-Dist: kiteconnect (>=4.1.0)
Requires-Dist: requests (>=2.28.1)
Provides-Extra: dev
Requires-Dist: ipdb ; extra == 'dev'
Requires-Dist: ipython ; extra == 'dev'
